meapi_core/__init__.py
meapi_core-0.0.1.dist-info/METADATA
meapi_core-0.0.1.dist-info/WHEEL
meapi_core-0.0.1.dist-info/top_level.txt
meapi_core-0.0.1.dist-info/RECORD
