Metadata-Version: 2.1
Name: meapi-core
Version: 0.0.1
Summary: MeAPI Core - Official Python SDK
Home-page: https://meapi.dev
Author: MeAPI Team
Author-email: dev@meapi.dev
Project-URL: Homepage, https://meapi.dev
Project-URL: Source, https://github.com/getmeapi/meapi
Classifier: Development Status :: 1 - Planning
Classifier: Intended Audience :: Developers
Classifier: License :: OSI Approved :: MIT License
Classifier: Programming Language :: Python :: 3
Requires-Python: >=3.8
